aeonsync/__init__.py
aeonsync/backup.py
aeonsync/cli.py
aeonsync/config.py
aeonsync/list.py
aeonsync/restore.py
aeonsync/utils.py
aeonsync-0.2.0.dist-info/LICENSE
aeonsync-0.2.0.dist-info/METADATA
aeonsync-0.2.0.dist-info/WHEEL
aeonsync-0.2.0.dist-info/entry_points.txt
aeonsync-0.2.0.dist-info/RECORD
