Metadata-Version: 2.1
Name: aeonsync
Version: 0.2.0
Summary: A simple but powerful rsync backup tool
License: GPLv3
Author: Stefanie Jane
Author-email: stef@hyperbliss.tech
Requires-Python: >=3.12,<4.0
Classifier: License :: Other/Proprietary License
Classifier: Programming Language :: Python :: 3
Classifier: Programming Language :: Python :: 3.12
Classifier: Programming Language :: Python :: 3.13
Requires-Dist: appdirs (>=1.4.4,<2.0.0)
Requires-Dist: colorama (>=0.4.6,<0.5.0)
Requires-Dist: prompt-toolkit (>=3.0.47,<4.0.0)
Requires-Dist: rich (>=13.8.0,<14.0.0)
Requires-Dist: toml (>=0.10.2,<0.11.0)
Requires-Dist: typer (>=0.12.5,<0.13.0)
